{
  "scraped_at": "2026-05-22 10:39:17 UTC",
  "source": "BBC News RSS",
  "total": 32,
  "headlines": [
    {
      "title": "Parents of Southport survivors say anonymity has erased their girls from the story",
      "link": "https://www.bbc.com/news/articles/c0j2q988x17o?at_medium=RSS&at_campaign=rss",
      "published": "Fri, 22 May 2026 05:00:03 GMT",
      "description": "The BBC has spoken to parents of some of the children who survived the knife attack, who believe they have been given insufficient support because of the anonymity order."
    },
    {
      "title": "Andrew investigation could look into sexual misconduct allegations",
      "link": "https://www.bbc.com/news/articles/c707l2jx0z4o?at_medium=RSS&at_campaign=rss",
      "published": "Fri, 22 May 2026 08:12:44 GMT",
      "description": "The former prince was arrested in February on suspicion of misconduct in public office."
    },
    {
      "title": "Stop blaming young people for being unemployed, says Amazon's UK boss",
      "link": "https://www.bbc.com/news/articles/c0l2x5351n4o?at_medium=RSS&at_campaign=rss",
      "published": "Fri, 22 May 2026 10:29:42 GMT",
      "description": "John Boumphrey says the education system \"isn't necessarily producing young people who are ready for work\"."
    },
    {
      "title": "Guardiola to leave Man City after 10 years as boss",
      "link": "https://www.bbc.com/sport/football/articles/cx21y7023qxo?at_medium=RSS&at_campaign=rss",
      "published": "Fri, 22 May 2026 10:38:04 GMT",
      "description": "Manchester City confirm that Pep Guardiola will leave at the end of the season after a decade of unparalleled success."
    },
    {
      "title": "Riskiest skin cancer cases hit UK record high",
      "link": "https://www.bbc.com/news/articles/c4g0ryrewdxo?at_medium=RSS&at_campaign=rss",
      "published": "Thu, 21 May 2026 23:15:18 GMT",
      "description": "The number of melanoma skin cancer cases has risen above 20,000 a year for the first time in the UK."
    },
    {
      "title": "Rubio says Cuba is threat to US as Havana accuses him of 'lies'",
      "link": "https://www.bbc.com/news/articles/ckgpzwkn5jko?at_medium=RSS&at_campaign=rss",
      "published": "Fri, 22 May 2026 08:13:13 GMT",
      "description": "Cuba's foreign minister accused Rubio of trying to \"instigate a military aggression\"."
    },
    {
      "title": "Reality TV risks sinking 'into the gutter', warns ex-Channel 4 and Ofcom boss Michael Grade",
      "link": "https://www.bbc.com/news/articles/c5yrkxge72eo?at_medium=RSS&at_campaign=rss",
      "published": "Fri, 22 May 2026 09:52:13 GMT",
      "description": "Michael Grade's warning comes in the wake of allegations made by participants on Married at First Sight."
    },
    {
      "title": "Rape sentences for teen boys unduly lenient, says Jess Phillips",
      "link": "https://www.bbc.com/news/articles/cwy2x7wxjego?at_medium=RSS&at_campaign=rss",
      "published": "Fri, 22 May 2026 10:33:39 GMT",
      "description": "The three teenagers avoided custodial sentences for their roles in the rape of two girls."
    },
    {
      "title": "Morrisons planning to close 100 stores in next few months",
      "link": "https://www.bbc.com/news/articles/c3623ny298xo?at_medium=RSS&at_campaign=rss",
      "published": "Fri, 22 May 2026 10:37:28 GMT",
      "description": "It said difficulties had been exacerbated by \"significant cost increases resulting from government policy choices\"."
    },
    {
      "title": "Alberta to hold referendum on whether to remain in Canada",
      "link": "https://www.bbc.com/news/articles/cvgze8n5dxko?at_medium=RSS&at_campaign=rss",
      "published": "Fri, 22 May 2026 02:40:58 GMT",
      "description": "Voters in the western province will decide next October whether they want to stay in Canada or move ahead with a process for a binding independence referendum."
    },
    {
      "title": "Maisie Peters on change, having a thick skin and her 'healed' sound",
      "link": "https://www.bbc.com/news/articles/cd7p4wzxn3qo?at_medium=RSS&at_campaign=rss",
      "published": "Fri, 22 May 2026 09:38:14 GMT",
      "description": "The singer shares what it has been like to grow up with her fans and the inspiration behind her new album."
    },
    {
      "title": "Cubans grapple with fuel shortages and blackouts as US steps up pressure",
      "link": "https://www.bbc.com/news/articles/c3e2w43lkvzo?at_medium=RSS&at_campaign=rss",
      "published": "Fri, 22 May 2026 09:32:42 GMT",
      "description": "The BBC speaks to Havana residents after the US charges the country's former leader, Raúl Castro, with murder."
    },
    {
      "title": "'Monitoring the situation': Why young men are drawn to prediction markets",
      "link": "https://www.bbc.com/news/articles/c93xv27kpwxo?at_medium=RSS&at_campaign=rss",
      "published": "Thu, 21 May 2026 23:09:43 GMT",
      "description": "Prediction markets are a fast-growing, multi-billion-dollar industry, and appeal disproportionately to young men"
    },
    {
      "title": "'We're meant to dance': Radio 1's Big Weekend has one focus on its first day",
      "link": "https://www.bbc.com/news/articles/c1d20dv05kro?at_medium=RSS&at_campaign=rss",
      "published": "Fri, 22 May 2026 00:01:27 GMT",
      "description": "Thousands are expected to attend this year's festival in Sunderland, with Fatboy Slim headlining on Friday."
    },
    {
      "title": "Hamnet author Maggie O'Farrell on her new novel and keeping her Bafta in the basement",
      "link": "https://www.bbc.com/news/articles/c202lev624xo?at_medium=RSS&at_campaign=rss",
      "published": "Fri, 22 May 2026 05:01:10 GMT",
      "description": "Maggie O'Farrell's new novel, Land, is published after the success of the film adaptation of Hamnet."
    },
    {
      "title": "'We are resilient': As San Diego's Muslim community reels from mosque shooting, it refuses to be intimidated",
      "link": "https://www.bbc.com/news/articles/clypx2pr52qo?at_medium=RSS&at_campaign=rss",
      "published": "Fri, 22 May 2026 01:49:43 GMT",
      "description": "Thousands attend funeral prayers for the three victims of Monday's deadly shooting at the Islamic Centre of San Diego."
    },
    {
      "title": "Weekly quiz: Eurovision went mad for Bangaranga - but who gave the UK its only point?",
      "link": "https://www.bbc.com/news/articles/c04216r5n07o?at_medium=RSS&at_campaign=rss",
      "published": "Thu, 21 May 2026 18:22:35 GMT",
      "description": "How much attention did you pay to what happened in the world over the past seven days?"
    },
    {
      "title": "Jessie J 'sobbed for hours' after hearing she is cancer-free",
      "link": "https://www.bbc.com/news/articles/crrpxzrgnppo?at_medium=RSS&at_campaign=rss",
      "published": "Fri, 22 May 2026 09:02:50 GMT",
      "description": "The singer says she \"exhaled for the first time in a year\" after doctors gave her the news."
    },
    {
      "title": "Stephen Colbert joined by Sir Paul McCartney for The Late Show finale",
      "link": "https://www.bbc.com/news/articles/cx21gnlx0w1o?at_medium=RSS&at_campaign=rss",
      "published": "Fri, 22 May 2026 06:19:04 GMT",
      "description": "The host joined Sir Paul and the band to close out the show with a performance of the Beatles' Hello, Goodbye."
    },
    {
      "title": "Nato chief welcomes US sending 5,000 troops to Poland",
      "link": "https://www.bbc.com/news/articles/cedpz9669deo?at_medium=RSS&at_campaign=rss",
      "published": "Fri, 22 May 2026 09:43:39 GMT",
      "description": "President Trump's announcement on Thursday night came ahead of a meeting of Nato foreign ministers."
    },
    {
      "title": "Queues at Dover start to build in first holiday getaway since new EU checks",
      "link": "https://www.bbc.com/news/articles/cpqpygjwywjo?at_medium=RSS&at_campaign=rss",
      "published": "Fri, 22 May 2026 09:04:55 GMT",
      "description": "It is the first holiday period since the EU's new border system was fully implemented."
    },
    {
      "title": "Former Green Party by-election candidate apologises for sharing 'false flag' post",
      "link": "https://www.bbc.com/news/articles/cq8pg0pke3qo?at_medium=RSS&at_campaign=rss",
      "published": "Fri, 22 May 2026 09:40:35 GMT",
      "description": "The Green Party had announced Chris Kennedy withdrew as candidate for \"personal and family reasons\"."
    },
    {
      "title": "Borrowing in April hit highest level since Covid",
      "link": "https://www.bbc.com/news/articles/ce9py7nx8j4o?at_medium=RSS&at_campaign=rss",
      "published": "Fri, 22 May 2026 09:36:13 GMT",
      "description": "Borrowing was higher than expected last month and retail sales fell as fuel prices surged."
    },
    {
      "title": "Slow Food founder Carlo Petrini dies aged 76",
      "link": "https://www.bbc.com/news/articles/cn9pe1py9zwo?at_medium=RSS&at_campaign=rss",
      "published": "Fri, 22 May 2026 10:22:21 GMT",
      "description": "Petrini's movement rejected fast food to promote sustainable production and traditional cooking."
    },
    {
      "title": "BBC News app",
      "link": "https://www.bbc.co.uk/news/10628994?at_medium=RSS&at_campaign=rss",
      "published": "Wed, 30 Apr 2025 14:04:28 GMT",
      "description": "Top stories, breaking news, live reporting, and follow news topics that match your interests"
    },
    {
      "title": "The Rachel Reeves \"Fun\" Tax Cuts",
      "link": "https://www.bbc.co.uk/sounds/play/p0nm3x2l?at_medium=RSS&at_campaign=rss",
      "published": "Thu, 21 May 2026 21:09:00 GMT",
      "description": "Cheaper amusement parks, theatre tickets and kid's meals."
    },
    {
      "title": "Trump gets 'forever' immunity on his past tax affairs",
      "link": "https://www.bbc.co.uk/sounds/play/p0nmcs7t?at_medium=RSS&at_campaign=rss",
      "published": "Wed, 20 May 2026 20:48:00 GMT",
      "description": "The US president's extraordinary new deal for himself and members of his family"
    },
    {
      "title": "Guardiola says 'nothing is eternal' as Man City exit confirmed",
      "link": "https://www.bbc.com/sport/football/articles/cx21y7023qxo?at_medium=RSS&at_campaign=rss",
      "published": "Fri, 22 May 2026 10:38:04 GMT",
      "description": "Manchester City confirm that Pep Guardiola will leave at the end of the season after a decade of unparalleled success."
    },
    {
      "title": "Carrick confirmed as Man Utd permanent boss",
      "link": "https://www.bbc.com/sport/football/articles/cd9pk7g3kelo?at_medium=RSS&at_campaign=rss",
      "published": "Fri, 22 May 2026 10:20:55 GMT",
      "description": "Manchester United confirm the appointment of Michael Carrick as their permanent head coach on a two-year contract."
    },
    {
      "title": "Foden, Palmer, Alexander-Arnold to miss World Cup",
      "link": "https://www.bbc.com/sport/football/articles/c78ke277pmdo?at_medium=RSS&at_campaign=rss",
      "published": "Fri, 22 May 2026 09:24:52 GMT",
      "description": "Phil Foden, Cole Palmer and Trent Alexander-Arnold have not been included in Thomas Tuchel's 26-man England squad for this summer's World Cup."
    },
    {
      "title": "How a kickboxing legend & Statham's pal landed a shot at Usyk",
      "link": "https://www.bbc.com/sport/boxing/articles/clypnr49dljo?at_medium=RSS&at_campaign=rss",
      "published": "Fri, 22 May 2026 05:18:19 GMT",
      "description": "Dutchman Rico Verhoeven discusses his kickboxing career, friendship with A-list celebrities and how he landed a shot at Oleksandr Usyk."
    },
    {
      "title": "Palmer and Foden lose ruthless Tuchel's battle for number 10 roles",
      "link": "https://www.bbc.com/sport/football/articles/c1k2g782m1ro?at_medium=RSS&at_campaign=rss",
      "published": "Thu, 21 May 2026 22:48:12 GMT",
      "description": "Two years ago Phil Foden and Cole Palmer were England's future. Now, they cannot even get into the squad amid fierce rivalry for the number 10 role."
    }
  ]
}